[
    {
        "name": "Architecture Decision Records",
        "ring": "trial",
        "quadrant": "techniques",
        "isNew": "TRUE",
        "description": "..."
    },
    {
        "name": "Conventional Commits",
        "ring": "trial",
        "quadrant": "techniques",
        "isNew": "TRUE",
        "description": "<p><a href=https://www.conventionalcommits.org/en/v1.0.0/>Conventional Commits</a></p>"
    },
    {
        "name": "Threat Modeling",
        "ring": "trial",
        "quadrant": "tools",
        "isNew": "TRUE",
        "description": "..."
    }
    {
        "name": "Mermaid",
        "ring": "trial",
        "quadrant": "tools",
        "isNew": "TRUE",
        "description": "<p><a href=https://mermaid.js.org/>Mermaid</a></p>"
    }
]
